ps_signal/__init__.py
ps_signal/__main__.py
ps_signal/interfaces/__init__.py
ps_signal/interfaces/cli/__init__.py
ps_signal/interfaces/cli/cli.py
ps_signal/interfaces/cli/cli_conf.py
ps_signal/interfaces/cli/strings.py
ps_signal/interfaces/gui/__init__.py
ps_signal/interfaces/gui/gui.py
ps_signal/signals/__init__.py
ps_signal/signals/data.py
ps_signal/signals/fft.py
ps_signal/signals/filters.py
ps_signal/signals/plot.py
ps_signal/signals/signal.py
ps_signal/signals/subsignal.py
ps_signal/utilities/__init__.py
ps_signal/utilities/decorators.py
ps_signal-0.1.8.dist-info/LICENSE
ps_signal-0.1.8.dist-info/METADATA
ps_signal-0.1.8.dist-info/WHEEL
ps_signal-0.1.8.dist-info/entry_points.txt
ps_signal-0.1.8.dist-info/top_level.txt
ps_signal-0.1.8.dist-info/RECORD
