Metadata-Version: 2.1
Name: ps-signal
Version: 0.1.8
Summary: Module for parsing and analysing data from a picoscope.
Home-page: UNKNOWN
Author: Robert Nyström
Author-email: golgafrincham@gmail.com
License: UNKNOWN
Project-URL: Documentation, https://ps-signal.readthedocs.io/en/latest/
Project-URL: Source, https://github.com/golgor/ps-signal/
Keywords: analysis,picoscope
Platform: UNKNOWN
Classifier: Development Status :: 3 - Alpha
Classifier: Intended Audience :: Developers
Classifier: Topic :: Software Development :: Build Tools
Classifier: Programming Language :: Python :: 3.6
Classifier: Programming Language :: Python :: 3.7
Classifier: Programming Language :: Python :: 3.8
Requires-Python: >=3.6, <4
Requires-Dist: matplotlib (>=3.1.3)
Requires-Dist: scipy (>=1.4.1)
Requires-Dist: numpy (>=1.18.1)
Requires-Dist: xlrd (>=1.2.0)
Requires-Dist: seaborn (>=0.10.0)
Requires-Dist: pandas (>=1.0.1)
